stationbench/__init__.py
stationbench/calculate_metrics.py
stationbench/cli.py
stationbench/compare_forecasts.py
stationbench/utils/__init__.py
stationbench/utils/formatting.py
stationbench/utils/io.py
stationbench/utils/logging.py
stationbench/utils/metrics.py
stationbench/utils/plotting.py
stationbench/utils/regions.py
stationbench-0.1.2.dist-info/LICENSE
stationbench-0.1.2.dist-info/METADATA
stationbench-0.1.2.dist-info/WHEEL
stationbench-0.1.2.dist-info/entry_points.txt
stationbench-0.1.2.dist-info/RECORD
