Metadata-Version: 2.1
Name: stationbench
Version: 0.1.2
Summary: A Python package for benchmarking weather forecasts against weather station data
License: MIT
Author: Jua.ai
Author-email: support@jua.ai
Requires-Python: >=3.11,<3.13
Classifier: License :: OSI Approved :: MIT License
Classifier: Programming Language :: Python :: 3
Classifier: Programming Language :: Python :: 3.11
Classifier: Programming Language :: Python :: 3.12
Requires-Dist: dask[distributed] (>=2024.1.1,<2025.0.0)
Requires-Dist: gcsfs (>=2024.2.0,<2025.0.0)
Requires-Dist: kaleido (==0.2.1)
Requires-Dist: nbformat (>=5.10.4,<6.0.0)
Requires-Dist: pandas (>=2.2.0,<3.0.0)
Requires-Dist: plotly (>=5.18.0,<6.0.0)
Requires-Dist: scipy (>=1.12.0,<2.0.0)
Requires-Dist: wandb (>=0.19.7,<0.20.0)
Requires-Dist: xarray (>=2024.1.1,<2025.0.0)
Requires-Dist: zarr (>=2.16.1,<3.0.0)
